claf/__init__.py
claf/__version__.py
claf/nsml.py
claf/utils.py
claf/config/__init__.py
claf/config/args.py
claf/config/namespace.py
claf/config/pattern.py
claf/config/registry.py
claf/config/utils.py
claf/config/factory/__init__.py
claf/config/factory/base.py
claf/config/factory/data_loader.py
claf/config/factory/data_reader.py
claf/config/factory/model.py
claf/config/factory/optimizer.py
claf/config/factory/tokens.py
claf/data/__init__.py
claf/data/batch.py
claf/data/collate.py
claf/data/data_handler.py
claf/data/utils.py
claf/data/dataset/__init__.py
claf/data/dataset/base.py
claf/data/dataset/seq_cls.py
claf/data/dataset/seq_cls_bert.py
claf/data/dataset/squad.py
claf/data/dataset/squad_bert.py
claf/data/dataset/tok_cls_bert.py
claf/data/dataset/wikisql.py
claf/data/dataset/bert/__init__.py
claf/data/dataset/bert/regression.py
claf/data/dataset/bert/seq_cls.py
claf/data/dataset/bert/squad.py
claf/data/dataset/bert/tok_cls.py
claf/data/dto/__init__.py
claf/data/dto/batch.py
claf/data/dto/bert_feature.py
claf/data/dto/helper.py
claf/data/reader/__init__.py
claf/data/reader/base.py
claf/data/reader/cola.py
claf/data/reader/seq_cls.py
claf/data/reader/squad.py
claf/data/reader/wikisql.py
claf/data/reader/bert/__init__.py
claf/data/reader/bert/cola.py
claf/data/reader/bert/conll2003.py
claf/data/reader/bert/regression.py
claf/data/reader/bert/seq_cls.py
claf/data/reader/bert/squad.py
claf/data/reader/bert/tok_cls.py
claf/data/reader/bert/glue/__init__.py
claf/data/reader/bert/glue/cola.py
claf/data/reader/bert/glue/mnli.py
claf/data/reader/bert/glue/mrpc.py
claf/data/reader/bert/glue/qnli.py
claf/data/reader/bert/glue/qqp.py
claf/data/reader/bert/glue/rte.py
claf/data/reader/bert/glue/sst.py
claf/data/reader/bert/glue/stsb.py
claf/data/reader/bert/glue/wnli.py
claf/decorator/__init__.py
claf/decorator/arguments.py
claf/decorator/register.py
claf/learn/__init__.py
claf/learn/experiment.py
claf/learn/mode.py
claf/learn/tensorboard.py
claf/learn/trainer.py
claf-0.2.0.dist-info/LICENSE
claf-0.2.0.dist-info/METADATA
claf-0.2.0.dist-info/NOTICE
claf-0.2.0.dist-info/WHEEL
claf-0.2.0.dist-info/top_level.txt
claf-0.2.0.dist-info/RECORD
