Metadata-Version: 2.1
Name: claf
Version: 0.2.0
Summary: CLaF: Clova Language Framework
Home-page: https://github.com/naver/claf
Author: Dongjun Lee
Author-email: humanbrain.djlee@gmail.com
License: MIT
Platform: UNKNOWN
Classifier: License :: OSI Approved :: MIT License
Classifier: Programming Language :: Python
Classifier: Programming Language :: Python :: 3
Classifier: Programming Language :: Python :: 3.6
Classifier: Programming Language :: Python :: Implementation :: CPython
Classifier: Programming Language :: Python :: Implementation :: PyPy
Requires-Python: >=3.6.0
Requires-Dist: numpy (>=1.15.0)
Requires-Dist: torch (>=1.0.1)
Requires-Dist: pytorch-transformers (==1.1.0)
Requires-Dist: konlpy
Requires-Dist: nltk
Requires-Dist: spacy
Requires-Dist: babel
Requires-Dist: records
Requires-Dist: h5py
Requires-Dist: jsbeautifier
Requires-Dist: msgpack
Requires-Dist: overrides
Requires-Dist: requests
Requires-Dist: gensim
Requires-Dist: tqdm
Requires-Dist: tensorboardX
Requires-Dist: pycm
Requires-Dist: seqeval
Requires-Dist: scikit-learn
